MANIFEST.in
README.txt
setup.py
turberfield/machina/__init__.py
turberfield/machina/company.py
turberfield/machina/shifter.py
turberfield/machina/stage.py
turberfield/machina/utils.py
turberfield/machina/demo/__init__.py
turberfield/machina/demo/elements.py
turberfield/machina/demo/main.py
turberfield/machina/demo/simulation.py
turberfield/machina/demo/static/css/animations.css
turberfield/machina/demo/static/css/base-min.css
turberfield/machina/demo/static/css/grids-responsive-min.css
turberfield/machina/demo/static/css/pure-min.css
turberfield/machina/demo/static/js/jquery-2.1.1.js
turberfield/machina/demo/static/js/knockout-3.2.0.js
turberfield/machina/demo/static/rson/demo.rson
turberfield/machina/demo/templates/gainsborough_square.tpl
turberfield/machina/demo/templates/option_list.tpl
turberfield/machina/demo/templates/simulation.tpl
turberfield/machina/doc/index.rst
turberfield/machina/doc/html/genindex.html
turberfield/machina/doc/html/index.html
turberfield/machina/doc/html/search.html
turberfield/machina/doc/html/searchindex.js
turberfield/machina/doc/html/_sources/index.txt
turberfield/machina/doc/html/_static/ajax-loader.gif
turberfield/machina/doc/html/_static/alert_info_32.png
turberfield/machina/doc/html/_static/alert_warning_32.png
turberfield/machina/doc/html/_static/basic.css
turberfield/machina/doc/html/_static/bg-page.png
turberfield/machina/doc/html/_static/bullet_orange.png
turberfield/machina/doc/html/_static/comment-bright.png
turberfield/machina/doc/html/_static/comment-close.png
turberfield/machina/doc/html/_static/comment.png
turberfield/machina/doc/html/_static/doctools.js
turberfield/machina/doc/html/_static/down-pressed.png
turberfield/machina/doc/html/_static/down.png
turberfield/machina/doc/html/_static/file.png
turberfield/machina/doc/html/_static/haiku.css
turberfield/machina/doc/html/_static/jquery-1.11.1.js
turberfield/machina/doc/html/_static/jquery.js
turberfield/machina/doc/html/_static/minus.png
turberfield_machina.egg-info/PKG-INFO
turberfield_machina.egg-info/SOURCES.txt
turberfield_machina.egg-info/dependency_links.txt
turberfield_machina.egg-info/entry_points.txt
turberfield_machina.egg-info/namespace_packages.txt
turberfield_machina.egg-info/not-zip-safe
turberfield_machina.egg-info/requires.txt
turberfield_machina.egg-info/top_level.txt