Metadata-Version: 1.1
Name: turberfield-machina
Version: 0.010.0
Summary: Semantic web-based movement for interactive storytelling.
Home-page: https://www.assembla.com/spaces/turberfield/messages
Author: D Haynes
Author-email: tundish@thuswise.org
License: UNKNOWN
Platform: UNKNOWN
Classifier: Operating System :: POSIX
Classifier: Programming Language :: Python :: 3.4
Classifier: License :: OSI Approved :: GNU Affero General Public License v3 or later (AGPLv3+)
